andfn/__init__.py
andfn/bounding.py
andfn/const_head.py
andfn/constants.py
andfn/dfn.py
andfn/element.py
andfn/fracture.py
andfn/geometry_functions.py
andfn/impermeable_object.py
andfn/intersection.py
andfn/math_functions.py
andfn/structures.py
andfn/well.py
andfn/hpc/__init__.py
andfn/hpc/hpc_bounding_circle.py
andfn/hpc/hpc_const_head_line.py
andfn/hpc/hpc_fracture.py
andfn/hpc/hpc_geometry_functions.py
andfn/hpc/hpc_imp_object.py
andfn/hpc/hpc_intersection.py
andfn/hpc/hpc_math_functions.py
andfn/hpc/hpc_solve.py
andfn/hpc/hpc_well.py
andfn-0.1.8.dist-info/licenses/LICENSE
andfn-0.1.8.dist-info/METADATA
andfn-0.1.8.dist-info/WHEEL
andfn-0.1.8.dist-info/top_level.txt
andfn-0.1.8.dist-info/RECORD
