Metadata-Version: 2.4
Name: andfn
Version: 0.1.8
Summary: An Analytic Element Model for Discrete Fracture Networks
Author: Erik A.L. Toller
Maintainer-email: "Erik A.L. Toller" <erik@toller.se>
License: MIT License
Project-URL: Homepage, https://eriktoller.github.io/andfn/n
Project-URL: Documentation, https://eriktoller.github.io/andfn/n
Project-URL: Repository, https://github.com/eriktoller/andfn
Project-URL: Issues, https://github.com/eriktoller/andfn/issues
Keywords: hydrology,groundwater,model,analytic element method,discrete fracture network,dfn
Classifier: Development Status :: 4 - Beta
Classifier: Intended Audience :: Science/Research
Classifier: Intended Audience :: Other Audience
Classifier: License :: OSI Approved :: MIT License
Classifier: Programming Language :: Python
Classifier: Topic :: Scientific/Engineering :: Hydrology
Requires-Python: >=3.11
License-File: LICENSE
Requires-Dist: numpy
Requires-Dist: pyvista~=0.44.2
Requires-Dist: scipy
Requires-Dist: numba~=0.61.2
Requires-Dist: h5py~=3.13.0
Provides-Extra: all
Requires-Dist: pyyaml; extra == "all"
Requires-Dist: pandas; extra == "all"
Requires-Dist: matplotlib; extra == "all"
Dynamic: license-file
